{
  "data": {
    "depression": [
      {
        "answer1": 9,
        "answer2": 9,
        "answer3": 4,
        "completed": true,
        "createdAt": 1686561120000,
        "id": 721,
        "modifiedAt": 1686561121010,
        "score": 22,
        "scoreLevel": "high"
      },
      {
        "answer1": 4,
        "answer2": 3,
        "answer3": 7,
        "completed": true,
        "createdAt": 1686561120000,
        "id": 722,
        "modifiedAt": 1686561121037,
        "score": 14,
        "scoreLevel": "moderate"
      },
      {
        "answer1": 1,
        "answer2": 6,
        "answer3": 9,
        "completed": true,
        "createdAt": 1686474721000,
        "id": 723,
        "modifiedAt": 1686561121064,
        "score": 16,
        "scoreLevel": "moderate"
      },
      {
        "answer1": 1,
        "answer2": 7,
        "answer3": 4,
        "completed": true,
        "createdAt": 1686474721000,
        "id": 724,
        "modifiedAt": 1686561121072,
        "score": 12,
        "scoreLevel": "moderate"
      },
      {
        "answer1": 0,
        "answer2": 9,
        "answer3": 4,
        "completed": true,
        "createdAt": 1686388321000,
        "id": 725,
        "modifiedAt": 1686561121081,
        "score": 13,
        "scoreLevel": "moderate"
      },
      {
        "answer1": 2,
        "answer2": 4,
        "answer3": 3,
        "completed": true,
        "createdAt": 1686388321000,
        "id": 726,
        "modifiedAt": 1686561121090,
        "score": 9,
        "scoreLevel": "low"
      },
      {
        "answer1": 7,
        "answer2": 0,
        "answer3": 6,
        "completed": true,
        "createdAt": 1686301921000,
        "id": 727,
        "modifiedAt": 1686561121112,
        "score": 13,
        "scoreLevel": "moderate"
      },
      {
        "answer1": 7,
        "answer2": 3,
        "answer3": 4,
        "completed": true,
        "createdAt": 1686301921000,
        "id": 728,
        "modifiedAt": 1686561121129,
        "score": 14,
        "scoreLevel": "moderate"
      },
      {
        "answer1": 8,
        "answer2": 3,
        "answer3": 2,
        "completed": true,
        "createdAt": 1686215521000,
        "id": 729,
        "modifiedAt": 1686561121138,
        "score": 13,
        "scoreLevel": "moderate"
      },
      {
        "answer1": 6,
        "answer2": 0,
        "answer3": 5,
        "completed": true,
        "createdAt": 1686215521000,
        "id": 730,
        "modifiedAt": 1686561121142,
        "score": 11,
        "scoreLevel": "moderate"
      },
      {
        "answer1": 5,
        "answer2": 7,
        "answer3": 7,
        "completed": true,
        "createdAt": 1686129121000,
        "id": 731,
        "modifiedAt": 1686561121148,
        "score": 19,
        "scoreLevel": "moderate"
      },
      {
        "answer1": 3,
        "answer2": 6,
        "answer3": 5,
        "completed": true,
        "createdAt": 1686129121000,
        "id": 732,
        "modifiedAt": 1686561121153,
        "score": 14,
        "scoreLevel": "moderate"
      },
      {
        "answer1": 6,
        "answer2": 7,
        "answer3": 0,
        "completed": true,
        "createdAt": 1686042721000,
        "id": 733,
        "modifiedAt": 1686561121171,
        "score": 13,
        "scoreLevel": "moderate"
      },
      {
        "answer1": 6,
        "answer2": 7,
        "answer3": 4,
        "completed": true,
        "createdAt": 1686042721000,
        "id": 734,
        "modifiedAt": 1686561121179,
        "score": 17,
        "scoreLevel": "moderate"
      },
      {
        "answer1": 6,
        "answer2": 2,
        "answer3": 8,
        "completed": true,
        "createdAt": 1685956321000,
        "id": 735,
        "modifiedAt": 1686561121187,
        "score": 16,
        "scoreLevel": "moderate"
      },
      {
        "answer1": 5,
        "answer2": 9,
        "answer3": 1,
        "completed": true,
        "createdAt": 1685956321000,
        "id": 736,
        "modifiedAt": 1686561121194,
        "score": 15,
        "scoreLevel": "moderate"
      },
      {
        "answer1": 8,
        "answer2": 1,
        "answer3": 3,
        "completed": true,
        "createdAt": 1685869921000,
        "id": 737,
        "modifiedAt": 1686561121200,
        "score": 12,
        "scoreLevel": "moderate"
      },
      {
        "answer1": 2,
        "answer2": 9,
        "answer3": 1,
        "completed": true,
        "createdAt": 1685869921000,
        "id": 738,
        "modifiedAt": 1686561121207,
        "score": 12,
        "scoreLevel": "moderate"
      },
      {
        "answer1": 3,
        "answer2": 4,
        "answer3": 6,
        "completed": true,
        "createdAt": 1685783521000,
        "id": 739,
        "modifiedAt": 1686561121214,
        "score": 13,
        "scoreLevel": "moderate"
      },
      {
        "answer1": 8,
        "answer2": 3,
        "answer3": 5,
        "completed": true,
        "createdAt": 1685783521000,
        "id": 740,
        "modifiedAt": 1686561121230,
        "score": 16,
        "scoreLevel": "moderate"
      },
      {
        "answer1": 1,
        "answer2": 5,
        "answer3": 4,
        "completed": true,
        "createdAt": 1685697121000,
        "id": 741,
        "modifiedAt": 1686561121238,
        "score": 10,
        "scoreLevel": "low"
      },
      {
        "answer1": 5,
        "answer2": 1,
        "answer3": 9,
        "completed": true,
        "createdAt": 1685697121000,
        "id": 742,
        "modifiedAt": 1686561121244,
        "score": 15,
        "scoreLevel": "moderate"
      },
      {
        "answer1": 4,
        "answer2": 5,
        "answer3": 1,
        "completed": true,
        "createdAt": 1685610721000,
        "id": 743,
        "modifiedAt": 1686561121251,
        "score": 10,
        "scoreLevel": "low"
      },
      {
        "answer1": 1,
        "answer2": 1,
        "answer3": 0,
        "completed": true,
        "createdAt": 1685610721000,
        "id": 744,
        "modifiedAt": 1686561121258,
        "score": 2,
        "scoreLevel": "low"
      },
      {
        "answer1": 2,
        "answer2": 6,
        "answer3": 8,
        "completed": true,
        "createdAt": 1685524321000,
        "id": 745,
        "modifiedAt": 1686561121264,
        "score": 16,
        "scoreLevel": "moderate"
      },
      {
        "answer1": 0,
        "answer2": 7,
        "answer3": 2,
        "completed": true,
        "createdAt": 1685524321000,
        "id": 746,
        "modifiedAt": 1686561121281,
        "score": 9,
        "scoreLevel": "low"
      },
      {
        "answer1": 2,
        "answer2": 7,
        "answer3": 7,
        "completed": true,
        "createdAt": 1685437921000,
        "id": 747,
        "modifiedAt": 1686561121289,
        "score": 16,
        "scoreLevel": "moderate"
      },
      {
        "answer1": 9,
        "answer2": 7,
        "answer3": 5,
        "completed": true,
        "createdAt": 1685437921000,
        "id": 748,
        "modifiedAt": 1686561121297,
        "score": 21,
        "scoreLevel": "high"
      },
      {
        "answer1": 3,
        "answer2": 2,
        "answer3": 7,
        "completed": true,
        "createdAt": 1685351521000,
        "id": 749,
        "modifiedAt": 1686561121306,
        "score": 12,
        "scoreLevel": "moderate"
      },
      {
        "answer1": 0,
        "answer2": 2,
        "answer3": 4,
        "completed": true,
        "createdAt": 1685351521000,
        "id": 750,
        "modifiedAt": 1686561121313,
        "score": 6,
        "scoreLevel": "low"
      },
      {
        "answer1": 9,
        "answer2": 2,
        "answer3": 7,
        "completed": true,
        "createdAt": 1685265121000,
        "id": 751,
        "modifiedAt": 1686561121339,
        "score": 18,
        "scoreLevel": "moderate"
      },
      {
        "answer1": 0,
        "answer2": 6,
        "answer3": 5,
        "completed": true,
        "createdAt": 1685265121000,
        "id": 752,
        "modifiedAt": 1686561121347,
        "score": 11,
        "scoreLevel": "moderate"
      },
      {
        "answer1": 8,
        "answer2": 1,
        "answer3": 8,
        "completed": true,
        "createdAt": 1685178721000,
        "id": 753,
        "modifiedAt": 1686561121359,
        "score": 17,
        "scoreLevel": "moderate"
      },
      {
        "answer1": 1,
        "answer2": 7,
        "answer3": 8,
        "completed": true,
        "createdAt": 1685178721000,
        "id": 754,
        "modifiedAt": 1686561121364,
        "score": 16,
        "scoreLevel": "moderate"
      },
      {
        "answer1": 5,
        "answer2": 7,
        "answer3": 9,
        "completed": true,
        "createdAt": 1685092321000,
        "id": 755,
        "modifiedAt": 1686561121372,
        "score": 21,
        "scoreLevel": "high"
      },
      {
        "answer1": 9,
        "answer2": 9,
        "answer3": 1,
        "completed": true,
        "createdAt": 1685092321000,
        "id": 756,
        "modifiedAt": 1686561121378,
        "score": 19,
        "scoreLevel": "moderate"
      },
      {
        "answer1": 1,
        "answer2": 6,
        "answer3": 8,
        "completed": true,
        "createdAt": 1685005921000,
        "id": 757,
        "modifiedAt": 1686561121385,
        "score": 15,
        "scoreLevel": "moderate"
      },
      {
        "answer1": 1,
        "answer2": 4,
        "answer3": 9,
        "completed": true,
        "createdAt": 1685005921000,
        "id": 758,
        "modifiedAt": 1686561121429,
        "score": 14,
        "scoreLevel": "moderate"
      },
      {
        "answer1": 7,
        "answer2": 8,
        "answer3": 6,
        "completed": true,
        "createdAt": 1684919521000,
        "id": 759,
        "modifiedAt": 1686561121443,
        "score": 21,
        "scoreLevel": "high"
      },
      {
        "answer1": 5,
        "answer2": 4,
        "answer3": 8,
        "completed": true,
        "createdAt": 1684919521000,
        "id": 760,
        "modifiedAt": 1686561121453,
        "score": 17,
        "scoreLevel": "moderate"
      },
      {
        "answer1": 3,
        "answer2": 2,
        "answer3": 0,
        "completed": true,
        "createdAt": 1684833121000,
        "id": 761,
        "modifiedAt": 1686561121465,
        "score": 5,
        "scoreLevel": "low"
      },
      {
        "answer1": 0,
        "answer2": 0,
        "answer3": 5,
        "completed": true,
        "createdAt": 1684833121000,
        "id": 762,
        "modifiedAt": 1686561121474,
        "score": 5,
        "scoreLevel": "low"
      },
      {
        "answer1": 1,
        "answer2": 3,
        "answer3": 3,
        "completed": true,
        "createdAt": 1684746721000,
        "id": 763,
        "modifiedAt": 1686561121485,
        "score": 7,
        "scoreLevel": "low"
      },
      {
        "answer1": 9,
        "answer2": 5,
        "answer3": 1,
        "completed": true,
        "createdAt": 1684746721000,
        "id": 764,
        "modifiedAt": 1686561121528,
        "score": 15,
        "scoreLevel": "moderate"
      },
      {
        "answer1": 5,
        "answer2": 5,
        "answer3": 5,
        "completed": true,
        "createdAt": 1684660321000,
        "id": 765,
        "modifiedAt": 1686561121539,
        "score": 15,
        "scoreLevel": "moderate"
      },
      {
        "answer1": 3,
        "answer2": 6,
        "answer3": 4,
        "completed": true,
        "createdAt": 1684660321000,
        "id": 766,
        "modifiedAt": 1686561121546,
        "score": 13,
        "scoreLevel": "moderate"
      },
      {
        "answer1": 2,
        "answer2": 4,
        "answer3": 9,
        "completed": true,
        "createdAt": 1684573921000,
        "id": 767,
        "modifiedAt": 1686561121554,
        "score": 15,
        "scoreLevel": "moderate"
      },
      {
        "answer1": 9,
        "answer2": 9,
        "answer3": 4,
        "completed": true,
        "createdAt": 1684573921000,
        "id": 768,
        "modifiedAt": 1686561121563,
        "score": 22,
        "scoreLevel": "high"
      },
      {
        "answer1": 9,
        "answer2": 0,
        "answer3": 1,
        "completed": true,
        "createdAt": 1684487521000,
        "id": 769,
        "modifiedAt": 1686561121575,
        "score": 10,
        "scoreLevel": "low"
      },
      {
        "answer1": 7,
        "answer2": 7,
        "answer3": 9,
        "completed": true,
        "createdAt": 1684487521000,
        "id": 770,
        "modifiedAt": 1686561121583,
        "score": 23,
        "scoreLevel": "high"
      },
      {
        "answer1": 7,
        "answer2": 9,
        "answer3": 5,
        "completed": true,
        "createdAt": 1684401121000,
        "id": 771,
        "modifiedAt": 1686561121603,
        "score": 21,
        "scoreLevel": "high"
      },
      {
        "answer1": 5,
        "answer2": 5,
        "answer3": 0,
        "completed": true,
        "createdAt": 1684401121000,
        "id": 772,
        "modifiedAt": 1686561121613,
        "score": 10,
        "scoreLevel": "low"
      },
      {
        "answer1": 9,
        "answer2": 2,
        "answer3": 6,
        "completed": true,
        "createdAt": 1684314721000,
        "id": 773,
        "modifiedAt": 1686561121626,
        "score": 17,
        "scoreLevel": "moderate"
      },
      {
        "answer1": 1,
        "answer2": 1,
        "answer3": 6,
        "completed": true,
        "createdAt": 1684314721000,
        "id": 774,
        "modifiedAt": 1686561121635,
        "score": 8,
        "scoreLevel": "low"
      },
      {
        "answer1": 5,
        "answer2": 0,
        "answer3": 3,
        "completed": true,
        "createdAt": 1684228321000,
        "id": 775,
        "modifiedAt": 1686561121646,
        "score": 8,
        "scoreLevel": "low"
      },
      {
        "answer1": 3,
        "answer2": 3,
        "answer3": 6,
        "completed": true,
        "createdAt": 1684228321000,
        "id": 776,
        "modifiedAt": 1686561121654,
        "score": 12,
        "scoreLevel": "moderate"
      },
      {
        "answer1": 0,
        "answer2": 6,
        "answer3": 7,
        "completed": true,
        "createdAt": 1684141921000,
        "id": 777,
        "modifiedAt": 1686561121673,
        "score": 13,
        "scoreLevel": "moderate"
      },
      {
        "answer1": 3,
        "answer2": 4,
        "answer3": 0,
        "completed": true,
        "createdAt": 1684141921000,
        "id": 778,
        "modifiedAt": 1686561121682,
        "score": 7,
        "scoreLevel": "low"
      },
      {
        "answer1": 4,
        "answer2": 2,
        "answer3": 2,
        "completed": true,
        "createdAt": 1684055521000,
        "id": 779,
        "modifiedAt": 1686561121699,
        "score": 8,
        "scoreLevel": "low"
      },
      {
        "answer1": 4,
        "answer2": 4,
        "answer3": 9,
        "completed": true,
        "createdAt": 1684055521000,
        "id": 780,
        "modifiedAt": 1686561121708,
        "score": 17,
        "scoreLevel": "moderate"
      }
    ],
    "loneliness": [
      {
        "answer1": 3,
        "answer2": 3,
        "answer3": 4,
        "answer4": 7,
        "completed": true,
        "createdAt": 1686561120000,
        "id": 721,
        "modifiedAt": 1686561121023,
        "score": 17,
        "scoreLevel": "moderate"
      },
      {
        "answer1": 6,
        "answer2": 3,
        "answer3": 5,
        "answer4": 7,
        "completed": true,
        "createdAt": 1686561120000,
        "id": 722,
        "modifiedAt": 1686561121039,
        "score": 21,
        "scoreLevel": "moderate"
      },
      {
        "answer1": 8,
        "answer2": 5,
        "answer3": 3,
        "answer4": 1,
        "completed": true,
        "createdAt": 1686474721000,
        "id": 723,
        "modifiedAt": 1686561121065,
        "score": 17,
        "scoreLevel": "moderate"
      },
      {
        "answer1": 5,
        "answer2": 3,
        "answer3": 4,
        "answer4": 5,
        "completed": true,
        "createdAt": 1686474721000,
        "id": 724,
        "modifiedAt": 1686561121075,
        "score": 17,
        "scoreLevel": "moderate"
      },
      {
        "answer1": 0,
        "answer2": 7,
        "answer3": 2,
        "answer4": 5,
        "completed": true,
        "createdAt": 1686388321000,
        "id": 725,
        "modifiedAt": 1686561121082,
        "score": 14,
        "scoreLevel": "moderate"
      },
      {
        "answer1": 1,
        "answer2": 1,
        "answer3": 0,
        "answer4": 5,
        "completed": true,
        "createdAt": 1686388321000,
        "id": 726,
        "modifiedAt": 1686561121091,
        "score": 7,
        "scoreLevel": "low"
      },
      {
        "answer1": 1,
        "answer2": 2,
        "answer3": 8,
        "answer4": 8,
        "completed": true,
        "createdAt": 1686301921000,
        "id": 727,
        "modifiedAt": 1686561121115,
        "score": 19,
        "scoreLevel": "moderate"
      },
      {
        "answer1": 6,
        "answer2": 2,
        "answer3": 2,
        "answer4": 8,
        "completed": true,
        "createdAt": 1686301921000,
        "id": 728,
        "modifiedAt": 1686561121130,
        "score": 18,
        "scoreLevel": "moderate"
      },
      {
        "answer1": 6,
        "answer2": 6,
        "answer3": 1,
        "answer4": 6,
        "completed": true,
        "createdAt": 1686215521000,
        "id": 729,
        "modifiedAt": 1686561121139,
        "score": 19,
        "scoreLevel": "moderate"
      },
      {
        "answer1": 3,
        "answer2": 2,
        "answer3": 5,
        "answer4": 1,
        "completed": true,
        "createdAt": 1686215521000,
        "id": 730,
        "modifiedAt": 1686561121143,
        "score": 11,
        "scoreLevel": "low"
      },
      {
        "answer1": 8,
        "answer2": 6,
        "answer3": 4,
        "answer4": 2,
        "completed": true,
        "createdAt": 1686129121000,
        "id": 731,
        "modifiedAt": 1686561121149,
        "score": 20,
        "scoreLevel": "moderate"
      },
      {
        "answer1": 8,
        "answer2": 7,
        "answer3": 8,
        "answer4": 5,
        "completed": true,
        "createdAt": 1686129121000,
        "id": 732,
        "modifiedAt": 1686561121153,
        "score": 28,
        "scoreLevel": "high"
      },
      {
        "answer1": 7,
        "answer2": 3,
        "answer3": 2,
        "answer4": 0,
        "completed": true,
        "createdAt": 1686042721000,
        "id": 733,
        "modifiedAt": 1686561121174,
        "score": 12,
        "scoreLevel": "low"
      },
      {
        "answer1": 6,
        "answer2": 0,
        "answer3": 9,
        "answer4": 9,
        "completed": true,
        "createdAt": 1686042721000,
        "id": 734,
        "modifiedAt": 1686561121180,
        "score": 24,
        "scoreLevel": "moderate"
      },
      {
        "answer1": 6,
        "answer2": 0,
        "answer3": 5,
        "answer4": 4,
        "completed": true,
        "createdAt": 1685956321000,
        "id": 735,
        "modifiedAt": 1686561121188,
        "score": 15,
        "scoreLevel": "moderate"
      },
      {
        "answer1": 3,
        "answer2": 1,
        "answer3": 9,
        "answer4": 7,
        "completed": true,
        "createdAt": 1685956321000,
        "id": 736,
        "modifiedAt": 1686561121195,
        "score": 20,
        "scoreLevel": "moderate"
      },
      {
        "answer1": 2,
        "answer2": 7,
        "answer3": 4,
        "answer4": 4,
        "completed": true,
        "createdAt": 1685869921000,
        "id": 737,
        "modifiedAt": 1686561121202,
        "score": 17,
        "scoreLevel": "moderate"
      },
      {
        "answer1": 2,
        "answer2": 6,
        "answer3": 2,
        "answer4": 7,
        "completed": true,
        "createdAt": 1685869921000,
        "id": 738,
        "modifiedAt": 1686561121209,
        "score": 17,
        "scoreLevel": "moderate"
      },
      {
        "answer1": 7,
        "answer2": 6,
        "answer3": 9,
        "answer4": 1,
        "completed": true,
        "createdAt": 1685783521000,
        "id": 739,
        "modifiedAt": 1686561121224,
        "score": 23,
        "scoreLevel": "moderate"
      },
      {
        "answer1": 4,
        "answer2": 0,
        "answer3": 7,
        "answer4": 5,
        "completed": true,
        "createdAt": 1685783521000,
        "id": 740,
        "modifiedAt": 1686561121231,
        "score": 16,
        "scoreLevel": "moderate"
      },
      {
        "answer1": 1,
        "answer2": 9,
        "answer3": 4,
        "answer4": 1,
        "completed": true,
        "createdAt": 1685697121000,
        "id": 741,
        "modifiedAt": 1686561121239,
        "score": 15,
        "scoreLevel": "moderate"
      },
      {
        "answer1": 6,
        "answer2": 0,
        "answer3": 8,
        "answer4": 3,
        "completed": true,
        "createdAt": 1685697121000,
        "id": 742,
        "modifiedAt": 1686561121245,
        "score": 17,
        "scoreLevel": "moderate"
      },
      {
        "answer1": 9,
        "answer2": 6,
        "answer3": 9,
        "answer4": 6,
        "completed": true,
        "createdAt": 1685610721000,
        "id": 743,
        "modifiedAt": 1686561121252,
        "score": 30,
        "scoreLevel": "high"
      },
      {
        "answer1": 3,
        "answer2": 6,
        "answer3": 7,
        "answer4": 8,
        "completed": true,
        "createdAt": 1685610721000,
        "id": 744,
        "modifiedAt": 1686561121259,
        "score": 24,
        "scoreLevel": "moderate"
      },
      {
        "answer1": 7,
        "answer2": 0,
        "answer3": 2,
        "answer4": 6,
        "completed": true,
        "createdAt": 1685524321000,
        "id": 745,
        "modifiedAt": 1686561121265,
        "score": 15,
        "scoreLevel": "moderate"
      },
      {
        "answer1": 4,
        "answer2": 3,
        "answer3": 1,
        "answer4": 2,
        "completed": true,
        "createdAt": 1685524321000,
        "id": 746,
        "modifiedAt": 1686561121282,
        "score": 10,
        "scoreLevel": "low"
      },
      {
        "answer1": 3,
        "answer2": 0,
        "answer3": 4,
        "answer4": 2,
        "completed": true,
        "createdAt": 1685437921000,
        "id": 747,
        "modifiedAt": 1686561121291,
        "score": 9,
        "scoreLevel": "low"
      },
      {
        "answer1": 7,
        "answer2": 5,
        "answer3": 7,
        "answer4": 7,
        "completed": true,
        "createdAt": 1685437921000,
        "id": 748,
        "modifiedAt": 1686561121299,
        "score": 26,
        "scoreLevel": "moderate"
      },
      {
        "answer1": 3,
        "answer2": 0,
        "answer3": 1,
        "answer4": 5,
        "completed": true,
        "createdAt": 1685351521000,
        "id": 749,
        "modifiedAt": 1686561121308,
        "score": 9,
        "scoreLevel": "low"
      },
      {
        "answer1": 9,
        "answer2": 5,
        "answer3": 1,
        "answer4": 6,
        "completed": true,
        "createdAt": 1685351521000,
        "id": 750,
        "modifiedAt": 1686561121314,
        "score": 21,
        "scoreLevel": "moderate"
      },
      {
        "answer1": 9,
        "answer2": 7,
        "answer3": 4,
        "answer4": 8,
        "completed": true,
        "createdAt": 1685265121000,
        "id": 751,
        "modifiedAt": 1686561121342,
        "score": 28,
        "scoreLevel": "high"
      },
      {
        "answer1": 9,
        "answer2": 9,
        "answer3": 9,
        "answer4": 8,
        "completed": true,
        "createdAt": 1685265121000,
        "id": 752,
        "modifiedAt": 1686561121348,
        "score": 35,
        "scoreLevel": "high"
      },
      {
        "answer1": 4,
        "answer2": 9,
        "answer3": 2,
        "answer4": 7,
        "completed": true,
        "createdAt": 1685178721000,
        "id": 753,
        "modifiedAt": 1686561121360,
        "score": 22,
        "scoreLevel": "moderate"
      },
      {
        "answer1": 7,
        "answer2": 3,
        "answer3": 4,
        "answer4": 0,
        "completed": true,
        "createdAt": 1685178721000,
        "id": 754,
        "modifiedAt": 1686561121365,
        "score": 14,
        "scoreLevel": "moderate"
      },
      {
        "answer1": 4,
        "answer2": 0,
        "answer3": 3,
        "answer4": 0,
        "completed": true,
        "createdAt": 1685092321000,
        "id": 755,
        "modifiedAt": 1686561121373,
        "score": 7,
        "scoreLevel": "low"
      },
      {
        "answer1": 8,
        "answer2": 6,
        "answer3": 6,
        "answer4": 5,
        "completed": true,
        "createdAt": 1685092321000,
        "id": 756,
        "modifiedAt": 1686561121379,
        "score": 25,
        "scoreLevel": "moderate"
      },
      {
        "answer1": 1,
        "answer2": 9,
        "answer3": 0,
        "answer4": 3,
        "completed": true,
        "createdAt": 1685005921000,
        "id": 757,
        "modifiedAt": 1686561121387,
        "score": 13,
        "scoreLevel": "low"
      },
      {
        "answer1": 6,
        "answer2": 8,
        "answer3": 7,
        "answer4": 9,
        "completed": true,
        "createdAt": 1685005921000,
        "id": 758,
        "modifiedAt": 1686561121431,
        "score": 30,
        "scoreLevel": "high"
      },
      {
        "answer1": 7,
        "answer2": 6,
        "answer3": 7,
        "answer4": 8,
        "completed": true,
        "createdAt": 1684919521000,
        "id": 759,
        "modifiedAt": 1686561121446,
        "score": 28,
        "scoreLevel": "high"
      },
      {
        "answer1": 9,
        "answer2": 9,
        "answer3": 5,
        "answer4": 7,
        "completed": true,
        "createdAt": 1684919521000,
        "id": 760,
        "modifiedAt": 1686561121456,
        "score": 30,
        "scoreLevel": "high"
      },
      {
        "answer1": 7,
        "answer2": 2,
        "answer3": 9,
        "answer4": 5,
        "completed": true,
        "createdAt": 1684833121000,
        "id": 761,
        "modifiedAt": 1686561121467,
        "score": 23,
        "scoreLevel": "moderate"
      },
      {
        "answer1": 3,
        "answer2": 5,
        "answer3": 6,
        "answer4": 2,
        "completed": true,
        "createdAt": 1684833121000,
        "id": 762,
        "modifiedAt": 1686561121476,
        "score": 16,
        "scoreLevel": "moderate"
      },
      {
        "answer1": 3,
        "answer2": 6,
        "answer3": 1,
        "answer4": 4,
        "completed": true,
        "createdAt": 1684746721000,
        "id": 763,
        "modifiedAt": 1686561121487,
        "score": 14,
        "scoreLevel": "moderate"
      },
      {
        "answer1": 5,
        "answer2": 6,
        "answer3": 2,
        "answer4": 1,
        "completed": true,
        "createdAt": 1684746721000,
        "id": 764,
        "modifiedAt": 1686561121530,
        "score": 14,
        "scoreLevel": "moderate"
      },
      {
        "answer1": 7,
        "answer2": 5,
        "answer3": 7,
        "answer4": 7,
        "completed": true,
        "createdAt": 1684660321000,
        "id": 765,
        "modifiedAt": 1686561121540,
        "score": 26,
        "scoreLevel": "moderate"
      },
      {
        "answer1": 7,
        "answer2": 3,
        "answer3": 1,
        "answer4": 7,
        "completed": true,
        "createdAt": 1684660321000,
        "id": 766,
        "modifiedAt": 1686561121547,
        "score": 18,
        "scoreLevel": "moderate"
      },
      {
        "answer1": 7,
        "answer2": 1,
        "answer3": 5,
        "answer4": 3,
        "completed": true,
        "createdAt": 1684573921000,
        "id": 767,
        "modifiedAt": 1686561121557,
        "score": 16,
        "scoreLevel": "moderate"
      },
      {
        "answer1": 5,
        "answer2": 0,
        "answer3": 8,
        "answer4": 4,
        "completed": true,
        "createdAt": 1684573921000,
        "id": 768,
        "modifiedAt": 1686561121564,
        "score": 17,
        "scoreLevel": "moderate"
      },
      {
        "answer1": 0,
        "answer2": 4,
        "answer3": 9,
        "answer4": 0,
        "completed": true,
        "createdAt": 1684487521000,
        "id": 769,
        "modifiedAt": 1686561121576,
        "score": 13,
        "scoreLevel": "low"
      },
      {
        "answer1": 8,
        "answer2": 8,
        "answer3": 6,
        "answer4": 2,
        "completed": true,
        "createdAt": 1684487521000,
        "id": 770,
        "modifiedAt": 1686561121594,
        "score": 24,
        "scoreLevel": "moderate"
      },
      {
        "answer1": 6,
        "answer2": 7,
        "answer3": 3,
        "answer4": 4,
        "completed": true,
        "createdAt": 1684401121000,
        "id": 771,
        "modifiedAt": 1686561121606,
        "score": 20,
        "scoreLevel": "moderate"
      },
      {
        "answer1": 8,
        "answer2": 9,
        "answer3": 9,
        "answer4": 1,
        "completed": true,
        "createdAt": 1684401121000,
        "id": 772,
        "modifiedAt": 1686561121616,
        "score": 27,
        "scoreLevel": "moderate"
      },
      {
        "answer1": 8,
        "answer2": 0,
        "answer3": 5,
        "answer4": 5,
        "completed": true,
        "createdAt": 1684314721000,
        "id": 773,
        "modifiedAt": 1686561121627,
        "score": 18,
        "scoreLevel": "moderate"
      },
      {
        "answer1": 9,
        "answer2": 9,
        "answer3": 7,
        "answer4": 5,
        "completed": true,
        "createdAt": 1684314721000,
        "id": 774,
        "modifiedAt": 1686561121636,
        "score": 30,
        "scoreLevel": "high"
      },
      {
        "answer1": 1,
        "answer2": 2,
        "answer3": 6,
        "answer4": 0,
        "completed": true,
        "createdAt": 1684228321000,
        "id": 775,
        "modifiedAt": 1686561121648,
        "score": 9,
        "scoreLevel": "low"
      },
      {
        "answer1": 1,
        "answer2": 1,
        "answer3": 2,
        "answer4": 5,
        "completed": true,
        "createdAt": 1684228321000,
        "id": 776,
        "modifiedAt": 1686561121655,
        "score": 9,
        "scoreLevel": "low"
      },
      {
        "answer1": 8,
        "answer2": 9,
        "answer3": 3,
        "answer4": 7,
        "completed": true,
        "createdAt": 1684141921000,
        "id": 777,
        "modifiedAt": 1686561121676,
        "score": 27,
        "scoreLevel": "moderate"
      },
      {
        "answer1": 0,
        "answer2": 9,
        "answer3": 2,
        "answer4": 4,
        "completed": true,
        "createdAt": 1684141921000,
        "id": 778,
        "modifiedAt": 1686561121683,
        "score": 15,
        "scoreLevel": "moderate"
      },
      {
        "answer1": 4,
        "answer2": 1,
        "answer3": 7,
        "answer4": 4,
        "completed": true,
        "createdAt": 1684055521000,
        "id": 779,
        "modifiedAt": 1686561121701,
        "score": 16,
        "scoreLevel": "moderate"
      },
      {
        "answer1": 5,
        "answer2": 4,
        "answer3": 4,
        "answer4": 9,
        "completed": true,
        "createdAt": 1684055521000,
        "id": 780,
        "modifiedAt": 1686561121710,
        "score": 22,
        "scoreLevel": "moderate"
      }
    ],
    "stress": [
      {
        "answer1": 8,
        "answer2": 8,
        "answer3": 8,
        "answer4": 7,
        "completed": true,
        "createdAt": 1686561120000,
        "id": 724,
        "modifiedAt": 1686561120997,
        "score": 31,
        "scoreLevel": "high"
      },
      {
        "answer1": 9,
        "answer2": 6,
        "answer3": 2,
        "answer4": 2,
        "completed": true,
        "createdAt": 1686561120000,
        "id": 725,
        "modifiedAt": 1686561121035,
        "score": 19,
        "scoreLevel": "moderate"
      },
      {
        "answer1": 6,
        "answer2": 9,
        "answer3": 4,
        "answer4": 4,
        "completed": true,
        "createdAt": 1686474721000,
        "id": 726,
        "modifiedAt": 1686561121063,
        "score": 23,
        "scoreLevel": "moderate"
      },
      {
        "answer1": 7,
        "answer2": 4,
        "answer3": 6,
        "answer4": 1,
        "completed": true,
        "createdAt": 1686474721000,
        "id": 727,
        "modifiedAt": 1686561121071,
        "score": 18,
        "scoreLevel": "moderate"
      },
      {
        "answer1": 2,
        "answer2": 8,
        "answer3": 0,
        "answer4": 9,
        "completed": true,
        "createdAt": 1686388321000,
        "id": 728,
        "modifiedAt": 1686561121080,
        "score": 19,
        "scoreLevel": "moderate"
      },
      {
        "answer1": 4,
        "answer2": 0,
        "answer3": 5,
        "answer4": 8,
        "completed": true,
        "createdAt": 1686388321000,
        "id": 729,
        "modifiedAt": 1686561121087,
        "score": 17,
        "scoreLevel": "moderate"
      },
      {
        "answer1": 1,
        "answer2": 3,
        "answer3": 0,
        "answer4": 7,
        "completed": true,
        "createdAt": 1686301921000,
        "id": 730,
        "modifiedAt": 1686561121111,
        "score": 11,
        "scoreLevel": "low"
      },
      {
        "answer1": 1,
        "answer2": 3,
        "answer3": 9,
        "answer4": 5,
        "completed": true,
        "createdAt": 1686301921000,
        "id": 731,
        "modifiedAt": 1686561121127,
        "score": 18,
        "scoreLevel": "moderate"
      },
      {
        "answer1": 7,
        "answer2": 3,
        "answer3": 6,
        "answer4": 9,
        "completed": true,
        "createdAt": 1686215521000,
        "id": 732,
        "modifiedAt": 1686561121137,
        "score": 25,
        "scoreLevel": "moderate"
      },
      {
        "answer1": 2,
        "answer2": 1,
        "answer3": 8,
        "answer4": 8,
        "completed": true,
        "createdAt": 1686215521000,
        "id": 733,
        "modifiedAt": 1686561121141,
        "score": 19,
        "scoreLevel": "moderate"
      },
      {
        "answer1": 6,
        "answer2": 0,
        "answer3": 0,
        "answer4": 1,
        "completed": true,
        "createdAt": 1686129121000,
        "id": 734,
        "modifiedAt": 1686561121147,
        "score": 7,
        "scoreLevel": "low"
      },
      {
        "answer1": 7,
        "answer2": 7,
        "answer3": 0,
        "answer4": 7,
        "completed": true,
        "createdAt": 1686129121000,
        "id": 735,
        "modifiedAt": 1686561121152,
        "score": 21,
        "scoreLevel": "moderate"
      },
      {
        "answer1": 7,
        "answer2": 2,
        "answer3": 1,
        "answer4": 2,
        "completed": true,
        "createdAt": 1686042721000,
        "id": 736,
        "modifiedAt": 1686561121168,
        "score": 12,
        "scoreLevel": "low"
      },
      {
        "answer1": 2,
        "answer2": 1,
        "answer3": 6,
        "answer4": 5,
        "completed": true,
        "createdAt": 1686042721000,
        "id": 737,
        "modifiedAt": 1686561121178,
        "score": 14,
        "scoreLevel": "moderate"
      },
      {
        "answer1": 3,
        "answer2": 4,
        "answer3": 9,
        "answer4": 2,
        "completed": true,
        "createdAt": 1685956321000,
        "id": 738,
        "modifiedAt": 1686561121186,
        "score": 18,
        "scoreLevel": "moderate"
      },
      {
        "answer1": 6,
        "answer2": 1,
        "answer3": 7,
        "answer4": 1,
        "completed": true,
        "createdAt": 1685956321000,
        "id": 739,
        "modifiedAt": 1686561121192,
        "score": 15,
        "scoreLevel": "moderate"
      },
      {
        "answer1": 3,
        "answer2": 6,
        "answer3": 4,
        "answer4": 9,
        "completed": true,
        "createdAt": 1685869921000,
        "id": 740,
        "modifiedAt": 1686561121199,
        "score": 22,
        "scoreLevel": "moderate"
      },
      {
        "answer1": 2,
        "answer2": 2,
        "answer3": 0,
        "answer4": 3,
        "completed": true,
        "createdAt": 1685869921000,
        "id": 741,
        "modifiedAt": 1686561121206,
        "score": 7,
        "scoreLevel": "low"
      },
      {
        "answer1": 2,
        "answer2": 7,
        "answer3": 4,
        "answer4": 8,
        "completed": true,
        "createdAt": 1685783521000,
        "id": 742,
        "modifiedAt": 1686561121213,
        "score": 21,
        "scoreLevel": "moderate"
      },
      {
        "answer1": 9,
        "answer2": 3,
        "answer3": 3,
        "answer4": 2,
        "completed": true,
        "createdAt": 1685783521000,
        "id": 743,
        "modifiedAt": 1686561121229,
        "score": 17,
        "scoreLevel": "moderate"
      },
      {
        "answer1": 8,
        "answer2": 0,
        "answer3": 5,
        "answer4": 3,
        "completed": true,
        "createdAt": 1685697121000,
        "id": 744,
        "modifiedAt": 1686561121237,
        "score": 16,
        "scoreLevel": "moderate"
      },
      {
        "answer1": 2,
        "answer2": 5,
        "answer3": 2,
        "answer4": 3,
        "completed": true,
        "createdAt": 1685697121000,
        "id": 745,
        "modifiedAt": 1686561121243,
        "score": 12,
        "scoreLevel": "low"
      },
      {
        "answer1": 5,
        "answer2": 1,
        "answer3": 9,
        "answer4": 0,
        "completed": true,
        "createdAt": 1685610721000,
        "id": 746,
        "modifiedAt": 1686561121250,
        "score": 15,
        "scoreLevel": "moderate"
      },
      {
        "answer1": 9,
        "answer2": 2,
        "answer3": 0,
        "answer4": 9,
        "completed": true,
        "createdAt": 1685610721000,
        "id": 747,
        "modifiedAt": 1686561121257,
        "score": 20,
        "scoreLevel": "moderate"
      },
      {
        "answer1": 5,
        "answer2": 7,
        "answer3": 2,
        "answer4": 7,
        "completed": true,
        "createdAt": 1685524321000,
        "id": 748,
        "modifiedAt": 1686561121263,
        "score": 21,
        "scoreLevel": "moderate"
      },
      {
        "answer1": 8,
        "answer2": 6,
        "answer3": 5,
        "answer4": 8,
        "completed": true,
        "createdAt": 1685524321000,
        "id": 749,
        "modifiedAt": 1686561121279,
        "score": 27,
        "scoreLevel": "moderate"
      },
      {
        "answer1": 6,
        "answer2": 6,
        "answer3": 0,
        "answer4": 0,
        "completed": true,
        "createdAt": 1685437921000,
        "id": 750,
        "modifiedAt": 1686561121288,
        "score": 12,
        "scoreLevel": "low"
      },
      {
        "answer1": 9,
        "answer2": 3,
        "answer3": 1,
        "answer4": 8,
        "completed": true,
        "createdAt": 1685437921000,
        "id": 751,
        "modifiedAt": 1686561121295,
        "score": 21,
        "scoreLevel": "moderate"
      },
      {
        "answer1": 9,
        "answer2": 8,
        "answer3": 2,
        "answer4": 1,
        "completed": true,
        "createdAt": 1685351521000,
        "id": 752,
        "modifiedAt": 1686561121305,
        "score": 20,
        "scoreLevel": "moderate"
      },
      {
        "answer1": 9,
        "answer2": 3,
        "answer3": 4,
        "answer4": 1,
        "completed": true,
        "createdAt": 1685351521000,
        "id": 753,
        "modifiedAt": 1686561121311,
        "score": 17,
        "scoreLevel": "moderate"
      },
      {
        "answer1": 4,
        "answer2": 3,
        "answer3": 2,
        "answer4": 9,
        "completed": true,
        "createdAt": 1685265121000,
        "id": 754,
        "modifiedAt": 1686561121329,
        "score": 18,
        "scoreLevel": "moderate"
      },
      {
        "answer1": 7,
        "answer2": 0,
        "answer3": 1,
        "answer4": 8,
        "completed": true,
        "createdAt": 1685265121000,
        "id": 755,
        "modifiedAt": 1686561121346,
        "score": 16,
        "scoreLevel": "moderate"
      },
      {
        "answer1": 5,
        "answer2": 5,
        "answer3": 4,
        "answer4": 2,
        "completed": true,
        "createdAt": 1685178721000,
        "id": 756,
        "modifiedAt": 1686561121357,
        "score": 16,
        "scoreLevel": "moderate"
      },
      {
        "answer1": 6,
        "answer2": 0,
        "answer3": 6,
        "answer4": 4,
        "completed": true,
        "createdAt": 1685178721000,
        "id": 757,
        "modifiedAt": 1686561121363,
        "score": 16,
        "scoreLevel": "moderate"
      },
      {
        "answer1": 9,
        "answer2": 8,
        "answer3": 7,
        "answer4": 7,
        "completed": true,
        "createdAt": 1685092321000,
        "id": 758,
        "modifiedAt": 1686561121370,
        "score": 31,
        "scoreLevel": "high"
      },
      {
        "answer1": 3,
        "answer2": 6,
        "answer3": 2,
        "answer4": 7,
        "completed": true,
        "createdAt": 1685092321000,
        "id": 759,
        "modifiedAt": 1686561121377,
        "score": 18,
        "scoreLevel": "moderate"
      },
      {
        "answer1": 5,
        "answer2": 2,
        "answer3": 9,
        "answer4": 0,
        "completed": true,
        "createdAt": 1685005921000,
        "id": 760,
        "modifiedAt": 1686561121384,
        "score": 16,
        "scoreLevel": "moderate"
      },
      {
        "answer1": 8,
        "answer2": 9,
        "answer3": 5,
        "answer4": 0,
        "completed": true,
        "createdAt": 1685005921000,
        "id": 761,
        "modifiedAt": 1686561121426,
        "score": 22,
        "scoreLevel": "moderate"
      },
      {
        "answer1": 2,
        "answer2": 9,
        "answer3": 7,
        "answer4": 6,
        "completed": true,
        "createdAt": 1684919521000,
        "id": 762,
        "modifiedAt": 1686561121442,
        "score": 24,
        "scoreLevel": "moderate"
      },
      {
        "answer1": 0,
        "answer2": 7,
        "answer3": 8,
        "answer4": 0,
        "completed": true,
        "createdAt": 1684919521000,
        "id": 763,
        "modifiedAt": 1686561121452,
        "score": 15,
        "scoreLevel": "moderate"
      },
      {
        "answer1": 8,
        "answer2": 7,
        "answer3": 7,
        "answer4": 8,
        "completed": true,
        "createdAt": 1684833121000,
        "id": 764,
        "modifiedAt": 1686561121464,
        "score": 30,
        "scoreLevel": "high"
      },
      {
        "answer1": 0,
        "answer2": 5,
        "answer3": 4,
        "answer4": 2,
        "completed": true,
        "createdAt": 1684833121000,
        "id": 765,
        "modifiedAt": 1686561121472,
        "score": 11,
        "scoreLevel": "low"
      },
      {
        "answer1": 0,
        "answer2": 9,
        "answer3": 0,
        "answer4": 0,
        "completed": true,
        "createdAt": 1684746721000,
        "id": 766,
        "modifiedAt": 1686561121483,
        "score": 9,
        "scoreLevel": "low"
      },
      {
        "answer1": 5,
        "answer2": 7,
        "answer3": 9,
        "answer4": 0,
        "completed": true,
        "createdAt": 1684746721000,
        "id": 767,
        "modifiedAt": 1686561121501,
        "score": 21,
        "scoreLevel": "moderate"
      },
      {
        "answer1": 6,
        "answer2": 4,
        "answer3": 2,
        "answer4": 4,
        "completed": true,
        "createdAt": 1684660321000,
        "id": 768,
        "modifiedAt": 1686561121537,
        "score": 16,
        "scoreLevel": "moderate"
      },
      {
        "answer1": 3,
        "answer2": 3,
        "answer3": 6,
        "answer4": 6,
        "completed": true,
        "createdAt": 1684660321000,
        "id": 769,
        "modifiedAt": 1686561121544,
        "score": 18,
        "scoreLevel": "moderate"
      },
      {
        "answer1": 0,
        "answer2": 9,
        "answer3": 9,
        "answer4": 7,
        "completed": true,
        "createdAt": 1684573921000,
        "id": 770,
        "modifiedAt": 1686561121553,
        "score": 25,
        "scoreLevel": "moderate"
      },
      {
        "answer1": 5,
        "answer2": 7,
        "answer3": 2,
        "answer4": 8,
        "completed": true,
        "createdAt": 1684573921000,
        "id": 771,
        "modifiedAt": 1686561121562,
        "score": 22,
        "scoreLevel": "moderate"
      },
      {
        "answer1": 5,
        "answer2": 5,
        "answer3": 7,
        "answer4": 2,
        "completed": true,
        "createdAt": 1684487521000,
        "id": 772,
        "modifiedAt": 1686561121573,
        "score": 19,
        "scoreLevel": "moderate"
      },
      {
        "answer1": 3,
        "answer2": 2,
        "answer3": 2,
        "answer4": 3,
        "completed": true,
        "createdAt": 1684487521000,
        "id": 773,
        "modifiedAt": 1686561121581,
        "score": 10,
        "scoreLevel": "low"
      },
      {
        "answer1": 1,
        "answer2": 1,
        "answer3": 7,
        "answer4": 8,
        "completed": true,
        "createdAt": 1684401121000,
        "id": 774,
        "modifiedAt": 1686561121602,
        "score": 17,
        "scoreLevel": "moderate"
      },
      {
        "answer1": 0,
        "answer2": 7,
        "answer3": 6,
        "answer4": 1,
        "completed": true,
        "createdAt": 1684401121000,
        "id": 775,
        "modifiedAt": 1686561121611,
        "score": 14,
        "scoreLevel": "moderate"
      },
      {
        "answer1": 8,
        "answer2": 9,
        "answer3": 6,
        "answer4": 5,
        "completed": true,
        "createdAt": 1684314721000,
        "id": 776,
        "modifiedAt": 1686561121624,
        "score": 28,
        "scoreLevel": "high"
      },
      {
        "answer1": 5,
        "answer2": 7,
        "answer3": 9,
        "answer4": 0,
        "completed": true,
        "createdAt": 1684314721000,
        "id": 777,
        "modifiedAt": 1686561121633,
        "score": 21,
        "scoreLevel": "moderate"
      },
      {
        "answer1": 1,
        "answer2": 0,
        "answer3": 6,
        "answer4": 4,
        "completed": true,
        "createdAt": 1684228321000,
        "id": 778,
        "modifiedAt": 1686561121645,
        "score": 11,
        "scoreLevel": "low"
      },
      {
        "answer1": 1,
        "answer2": 1,
        "answer3": 8,
        "answer4": 0,
        "completed": true,
        "createdAt": 1684228321000,
        "id": 779,
        "modifiedAt": 1686561121652,
        "score": 10,
        "scoreLevel": "low"
      },
      {
        "answer1": 5,
        "answer2": 5,
        "answer3": 7,
        "answer4": 1,
        "completed": true,
        "createdAt": 1684141921000,
        "id": 780,
        "modifiedAt": 1686561121672,
        "score": 18,
        "scoreLevel": "moderate"
      },
      {
        "answer1": 3,
        "answer2": 7,
        "answer3": 6,
        "answer4": 2,
        "completed": true,
        "createdAt": 1684141921000,
        "id": 781,
        "modifiedAt": 1686561121681,
        "score": 18,
        "scoreLevel": "moderate"
      },
      {
        "answer1": 9,
        "answer2": 9,
        "answer3": 2,
        "answer4": 5,
        "completed": true,
        "createdAt": 1684055521000,
        "id": 782,
        "modifiedAt": 1686561121698,
        "score": 25,
        "scoreLevel": "moderate"
      },
      {
        "answer1": 6,
        "answer2": 7,
        "answer3": 6,
        "answer4": 3,
        "completed": true,
        "createdAt": 1684055521000,
        "id": 783,
        "modifiedAt": 1686561121706,
        "score": 22,
        "scoreLevel": "moderate"
      }
    ],
    "suicide": [
      {
        "answer1": 0,
        "answer2": 0,
        "answer3": 0,
        "completed": true,
        "createdAt": 1686561120000,
        "id": 722,
        "modifiedAt": 1686561121029
      },
      {
        "answer1": 0,
        "answer2": 0,
        "answer3": 0,
        "completed": true,
        "createdAt": 1686561120000,
        "id": 723,
        "modifiedAt": 1686561121040
      },
      {
        "answer1": 0,
        "answer2": 0,
        "answer3": 0,
        "completed": true,
        "createdAt": 1686474721000,
        "id": 724,
        "modifiedAt": 1686561121066
      },
      {
        "answer1": 0,
        "answer2": 0,
        "answer3": 0,
        "completed": true,
        "createdAt": 1686474721000,
        "id": 725,
        "modifiedAt": 1686561121077
      },
      {
        "answer1": 0,
        "answer2": 0,
        "answer3": 0,
        "completed": true,
        "createdAt": 1686388321000,
        "id": 726,
        "modifiedAt": 1686561121084
      },
      {
        "answer1": 0,
        "answer2": 0,
        "answer3": 0,
        "completed": true,
        "createdAt": 1686388321000,
        "id": 727,
        "modifiedAt": 1686561121093
      },
      {
        "answer1": 0,
        "answer2": 0,
        "answer3": 0,
        "completed": true,
        "createdAt": 1686301921000,
        "id": 728,
        "modifiedAt": 1686561121118
      },
      {
        "answer1": 0,
        "answer2": 0,
        "answer3": 0,
        "completed": true,
        "createdAt": 1686301921000,
        "id": 729,
        "modifiedAt": 1686561121131
      },
      {
        "answer1": 0,
        "answer2": 0,
        "answer3": 0,
        "completed": true,
        "createdAt": 1686215521000,
        "id": 730,
        "modifiedAt": 1686561121140
      },
      {
        "answer1": 0,
        "answer2": 0,
        "answer3": 0,
        "completed": true,
        "createdAt": 1686215521000,
        "id": 731,
        "modifiedAt": 1686561121144
      },
      {
        "answer1": 0,
        "answer2": 0,
        "answer3": 0,
        "completed": true,
        "createdAt": 1686129121000,
        "id": 732,
        "modifiedAt": 1686561121150
      },
      {
        "answer1": 0,
        "answer2": 0,
        "answer3": 0,
        "completed": true,
        "createdAt": 1686129121000,
        "id": 733,
        "modifiedAt": 1686561121155
      },
      {
        "answer1": 0,
        "answer2": 0,
        "answer3": 0,
        "completed": true,
        "createdAt": 1686042721000,
        "id": 734,
        "modifiedAt": 1686561121175
      },
      {
        "answer1": 0,
        "answer2": 0,
        "answer3": 0,
        "completed": true,
        "createdAt": 1686042721000,
        "id": 735,
        "modifiedAt": 1686561121181
      },
      {
        "answer1": 0,
        "answer2": 0,
        "answer3": 0,
        "completed": true,
        "createdAt": 1685956321000,
        "id": 736,
        "modifiedAt": 1686561121189
      },
      {
        "answer1": 0,
        "answer2": 0,
        "answer3": 0,
        "completed": true,
        "createdAt": 1685956321000,
        "id": 737,
        "modifiedAt": 1686561121196
      },
      {
        "answer1": 0,
        "answer2": 0,
        "answer3": 0,
        "completed": true,
        "createdAt": 1685869921000,
        "id": 738,
        "modifiedAt": 1686561121203
      },
      {
        "answer1": 0,
        "answer2": 0,
        "answer3": 0,
        "completed": true,
        "createdAt": 1685869921000,
        "id": 739,
        "modifiedAt": 1686561121209
      },
      {
        "answer1": 0,
        "answer2": 0,
        "answer3": 0,
        "completed": true,
        "createdAt": 1685783521000,
        "id": 740,
        "modifiedAt": 1686561121226
      },
      {
        "answer1": 0,
        "answer2": 0,
        "answer3": 0,
        "completed": true,
        "createdAt": 1685783521000,
        "id": 741,
        "modifiedAt": 1686561121233
      },
      {
        "answer1": 0,
        "answer2": 0,
        "answer3": 0,
        "completed": true,
        "createdAt": 1685697121000,
        "id": 742,
        "modifiedAt": 1686561121241
      },
      {
        "answer1": 0,
        "answer2": 0,
        "answer3": 0,
        "completed": true,
        "createdAt": 1685697121000,
        "id": 743,
        "modifiedAt": 1686561121247
      },
      {
        "answer1": 0,
        "answer2": 0,
        "answer3": 0,
        "completed": true,
        "createdAt": 1685610721000,
        "id": 744,
        "modifiedAt": 1686561121254
      },
      {
        "answer1": 0,
        "answer2": 0,
        "answer3": 0,
        "completed": true,
        "createdAt": 1685610721000,
        "id": 745,
        "modifiedAt": 1686561121260
      },
      {
        "answer1": 0,
        "answer2": 0,
        "answer3": 0,
        "completed": true,
        "createdAt": 1685524321000,
        "id": 746,
        "modifiedAt": 1686561121266
      },
      {
        "answer1": 0,
        "answer2": 0,
        "answer3": 0,
        "completed": true,
        "createdAt": 1685524321000,
        "id": 747,
        "modifiedAt": 1686561121283
      },
      {
        "answer1": 0,
        "answer2": 0,
        "answer3": 0,
        "completed": true,
        "createdAt": 1685437921000,
        "id": 748,
        "modifiedAt": 1686561121292
      },
      {
        "answer1": 0,
        "answer2": 0,
        "answer3": 0,
        "completed": true,
        "createdAt": 1685437921000,
        "id": 749,
        "modifiedAt": 1686561121301
      },
      {
        "answer1": 0,
        "answer2": 0,
        "answer3": 0,
        "completed": true,
        "createdAt": 1685351521000,
        "id": 750,
        "modifiedAt": 1686561121309
      },
      {
        "answer1": 0,
        "answer2": 0,
        "answer3": 0,
        "completed": true,
        "createdAt": 1685351521000,
        "id": 751,
        "modifiedAt": 1686561121315
      },
      {
        "answer1": 0,
        "answer2": 0,
        "answer3": 0,
        "completed": true,
        "createdAt": 1685265121000,
        "id": 752,
        "modifiedAt": 1686561121343
      },
      {
        "answer1": 0,
        "answer2": 0,
        "answer3": 0,
        "completed": true,
        "createdAt": 1685265121000,
        "id": 753,
        "modifiedAt": 1686561121351
      },
      {
        "answer1": 0,
        "answer2": 0,
        "answer3": 0,
        "completed": true,
        "createdAt": 1685178721000,
        "id": 754,
        "modifiedAt": 1686561121361
      },
      {
        "answer1": 0,
        "answer2": 0,
        "answer3": 0,
        "completed": true,
        "createdAt": 1685178721000,
        "id": 755,
        "modifiedAt": 1686561121367
      },
      {
        "answer1": 0,
        "answer2": 0,
        "answer3": 0,
        "completed": true,
        "createdAt": 1685092321000,
        "id": 756,
        "modifiedAt": 1686561121375
      },
      {
        "answer1": 0,
        "answer2": 0,
        "answer3": 0,
        "completed": true,
        "createdAt": 1685092321000,
        "id": 757,
        "modifiedAt": 1686561121380
      },
      {
        "answer1": 0,
        "answer2": 0,
        "answer3": 0,
        "completed": true,
        "createdAt": 1685005921000,
        "id": 758,
        "modifiedAt": 1686561121405
      },
      {
        "answer1": 0,
        "answer2": 0,
        "answer3": 0,
        "completed": true,
        "createdAt": 1685005921000,
        "id": 759,
        "modifiedAt": 1686561121433
      },
      {
        "answer1": 0,
        "answer2": 0,
        "answer3": 0,
        "completed": true,
        "createdAt": 1684919521000,
        "id": 760,
        "modifiedAt": 1686561121448
      },
      {
        "answer1": 0,
        "answer2": 0,
        "answer3": 0,
        "completed": true,
        "createdAt": 1684919521000,
        "id": 761,
        "modifiedAt": 1686561121457
      },
      {
        "answer1": 0,
        "answer2": 0,
        "answer3": 0,
        "completed": true,
        "createdAt": 1684833121000,
        "id": 762,
        "modifiedAt": 1686561121468
      },
      {
        "answer1": 0,
        "answer2": 0,
        "answer3": 0,
        "completed": true,
        "createdAt": 1684833121000,
        "id": 763,
        "modifiedAt": 1686561121478
      },
      {
        "answer1": 0,
        "answer2": 0,
        "answer3": 0,
        "completed": true,
        "createdAt": 1684746721000,
        "id": 764,
        "modifiedAt": 1686561121489
      },
      {
        "answer1": 0,
        "answer2": 0,
        "answer3": 0,
        "completed": true,
        "createdAt": 1684746721000,
        "id": 765,
        "modifiedAt": 1686561121532
      },
      {
        "answer1": 0,
        "answer2": 0,
        "answer3": 0,
        "completed": true,
        "createdAt": 1684660321000,
        "id": 766,
        "modifiedAt": 1686561121542
      },
      {
        "answer1": 0,
        "answer2": 0,
        "answer3": 0,
        "completed": true,
        "createdAt": 1684660321000,
        "id": 767,
        "modifiedAt": 1686561121548
      },
      {
        "answer1": 0,
        "answer2": 0,
        "answer3": 0,
        "completed": true,
        "createdAt": 1684573921000,
        "id": 768,
        "modifiedAt": 1686561121559
      },
      {
        "answer1": 0,
        "answer2": 0,
        "answer3": 0,
        "completed": true,
        "createdAt": 1684573921000,
        "id": 769,
        "modifiedAt": 1686561121565
      },
      {
        "answer1": 0,
        "answer2": 0,
        "answer3": 0,
        "completed": true,
        "createdAt": 1684487521000,
        "id": 770,
        "modifiedAt": 1686561121578
      },
      {
        "answer1": 0,
        "answer2": 0,
        "answer3": 0,
        "completed": true,
        "createdAt": 1684487521000,
        "id": 771,
        "modifiedAt": 1686561121597
      },
      {
        "answer1": 0,
        "answer2": 0,
        "answer3": 0,
        "completed": true,
        "createdAt": 1684401121000,
        "id": 772,
        "modifiedAt": 1686561121608
      },
      {
        "answer1": 0,
        "answer2": 0,
        "answer3": 0,
        "completed": true,
        "createdAt": 1684401121000,
        "id": 773,
        "modifiedAt": 1686561121618
      },
      {
        "answer1": 0,
        "answer2": 0,
        "answer3": 0,
        "completed": true,
        "createdAt": 1684314721000,
        "id": 774,
        "modifiedAt": 1686561121629
      },
      {
        "answer1": 0,
        "answer2": 0,
        "answer3": 0,
        "completed": true,
        "createdAt": 1684314721000,
        "id": 775,
        "modifiedAt": 1686561121637
      },
      {
        "answer1": 0,
        "answer2": 0,
        "answer3": 0,
        "completed": true,
        "createdAt": 1684228321000,
        "id": 776,
        "modifiedAt": 1686561121649
      },
      {
        "answer1": 0,
        "answer2": 0,
        "answer3": 0,
        "completed": true,
        "createdAt": 1684228321000,
        "id": 777,
        "modifiedAt": 1686561121656
      },
      {
        "answer1": 0,
        "answer2": 0,
        "answer3": 0,
        "completed": true,
        "createdAt": 1684141921000,
        "id": 778,
        "modifiedAt": 1686561121677
      },
      {
        "answer1": 0,
        "answer2": 0,
        "answer3": 0,
        "completed": true,
        "createdAt": 1684141921000,
        "id": 779,
        "modifiedAt": 1686561121686
      },
      {
        "answer1": 0,
        "answer2": 0,
        "answer3": 0,
        "completed": true,
        "createdAt": 1684055521000,
        "id": 780,
        "modifiedAt": 1686561121704
      },
      {
        "answer1": 0,
        "answer2": 0,
        "answer3": 0,
        "completed": true,
        "createdAt": 1684055521000,
        "id": 781,
        "modifiedAt": 1686561121711
      }
    ],
    "symptoms": [
      {
        "appetite": "Appropriate",
        "completed": true,
        "createdAt": 1686561120000,
        "energy": "High",
        "focus": "Satisfactory",
        "id": 362,
        "libido": "Moderate",
        "modifiedAt": 1686561121042,
        "pain": "ModeratePain",
        "rest": "Satisfactory"
      },
      {
        "appetite": "Appropriate",
        "completed": true,
        "createdAt": 1686474721000,
        "energy": "High",
        "focus": "Satisfactory",
        "id": 363,
        "libido": "Moderate",
        "modifiedAt": 1686561121078,
        "pain": "ModeratePain",
        "rest": "Moderate"
      },
      {
        "appetite": "Appropriate",
        "completed": true,
        "createdAt": 1686388321000,
        "energy": "High",
        "focus": "Moderate",
        "id": 364,
        "libido": "Satisfactory",
        "modifiedAt": 1686561121094,
        "pain": "NoPain",
        "rest": "Moderate"
      },
      {
        "appetite": "Appropriate",
        "completed": true,
        "createdAt": 1686301921000,
        "energy": "High",
        "focus": "Moderate",
        "id": 365,
        "libido": "Satisfactory",
        "modifiedAt": 1686561121134,
        "pain": "NoPain",
        "rest": "Satisfactory"
      },
      {
        "appetite": "Appropriate",
        "completed": true,
        "createdAt": 1686215521000,
        "energy": "Moderate",
        "focus": "Satisfactory",
        "id": 366,
        "libido": "Moderate",
        "modifiedAt": 1686561121145,
        "pain": "ModeratePain",
        "rest": "Satisfactory"
      },
      {
        "appetite": "ExcessivelyHigh",
        "completed": true,
        "createdAt": 1686129121000,
        "energy": "Moderate",
        "focus": "Satisfactory",
        "id": 367,
        "libido": "Moderate",
        "modifiedAt": 1686561121156,
        "pain": "ModeratePain",
        "rest": "Satisfactory"
      },
      {
        "appetite": "ExcessivelyHigh",
        "completed": true,
        "createdAt": 1686042721000,
        "energy": "Moderate",
        "focus": "Moderate",
        "id": 368,
        "libido": "Satisfactory",
        "modifiedAt": 1686561121183,
        "pain": "ModeratePain",
        "rest": "Moderate"
      },
      {
        "appetite": "ExcessivelyHigh",
        "completed": true,
        "createdAt": 1685956321000,
        "energy": "High",
        "focus": "Moderate",
        "id": 369,
        "libido": "Satisfactory",
        "modifiedAt": 1686561121197,
        "pain": "ModeratePain",
        "rest": "Satisfactory"
      },
      {
        "appetite": "Appropriate",
        "completed": true,
        "createdAt": 1685869921000,
        "energy": "High",
        "focus": "Moderate",
        "id": 370,
        "libido": "Moderate",
        "modifiedAt": 1686561121210,
        "pain": "ModeratePain",
        "rest": "Satisfactory"
      },
      {
        "appetite": "ExcessivelyHigh",
        "completed": true,
        "createdAt": 1685783521000,
        "energy": "High",
        "focus": "Moderate",
        "id": 371,
        "libido": "Satisfactory",
        "modifiedAt": 1686561121234,
        "pain": "ModeratePain",
        "rest": "Moderate"
      },
      {
        "appetite": "ExcessivelyHigh",
        "completed": true,
        "createdAt": 1685697121000,
        "energy": "Moderate",
        "focus": "Moderate",
        "id": 372,
        "libido": "Satisfactory",
        "modifiedAt": 1686561121248,
        "pain": "NoPain",
        "rest": "Moderate"
      },
      {
        "appetite": "Appropriate",
        "completed": true,
        "createdAt": 1685610721000,
        "energy": "High",
        "focus": "Moderate",
        "id": 373,
        "libido": "Satisfactory",
        "modifiedAt": 1686561121261,
        "pain": "NoPain",
        "rest": "Satisfactory"
      },
      {
        "appetite": "ExcessivelyHigh",
        "completed": true,
        "createdAt": 1685524321000,
        "energy": "High",
        "focus": "Moderate",
        "id": 374,
        "libido": "Satisfactory",
        "modifiedAt": 1686561121284,
        "pain": "NoPain",
        "rest": "Moderate"
      },
      {
        "appetite": "ExcessivelyHigh",
        "completed": true,
        "createdAt": 1685437921000,
        "energy": "Moderate",
        "focus": "Moderate",
        "id": 375,
        "libido": "Moderate",
        "modifiedAt": 1686561121302,
        "pain": "ModeratePain",
        "rest": "Satisfactory"
      },
      {
        "appetite": "ExcessivelyHigh",
        "completed": true,
        "createdAt": 1685351521000,
        "energy": "Moderate",
        "focus": "Satisfactory",
        "id": 376,
        "libido": "Satisfactory",
        "modifiedAt": 1686561121316,
        "pain": "ModeratePain",
        "rest": "Satisfactory"
      },
      {
        "appetite": "Appropriate",
        "completed": true,
        "createdAt": 1685265121000,
        "energy": "High",
        "focus": "Satisfactory",
        "id": 377,
        "libido": "Satisfactory",
        "modifiedAt": 1686561121352,
        "pain": "NoPain",
        "rest": "Moderate"
      },
      {
        "appetite": "Appropriate",
        "completed": true,
        "createdAt": 1685178721000,
        "energy": "Moderate",
        "focus": "Satisfactory",
        "id": 378,
        "libido": "Moderate",
        "modifiedAt": 1686561121367,
        "pain": "NoPain",
        "rest": "Satisfactory"
      },
      {
        "appetite": "ExcessivelyHigh",
        "completed": true,
        "createdAt": 1685092321000,
        "energy": "Moderate",
        "focus": "Satisfactory",
        "id": 379,
        "libido": "Moderate",
        "modifiedAt": 1686561121381,
        "pain": "NoPain",
        "rest": "Satisfactory"
      },
      {
        "appetite": "Appropriate",
        "completed": true,
        "createdAt": 1685005921000,
        "energy": "Moderate",
        "focus": "Moderate",
        "id": 380,
        "libido": "Moderate",
        "modifiedAt": 1686561121436,
        "pain": "ModeratePain",
        "rest": "Satisfactory"
      },
      {
        "appetite": "Appropriate",
        "completed": true,
        "createdAt": 1684919521000,
        "energy": "Moderate",
        "focus": "Satisfactory",
        "id": 381,
        "libido": "Moderate",
        "modifiedAt": 1686561121460,
        "pain": "NoPain",
        "rest": "Satisfactory"
      },
      {
        "appetite": "Appropriate",
        "completed": true,
        "createdAt": 1684833121000,
        "energy": "High",
        "focus": "Satisfactory",
        "id": 382,
        "libido": "Moderate",
        "modifiedAt": 1686561121480,
        "pain": "ModeratePain",
        "rest": "Satisfactory"
      },
      {
        "appetite": "ExcessivelyHigh",
        "completed": true,
        "createdAt": 1684746721000,
        "energy": "High",
        "focus": "Satisfactory",
        "id": 383,
        "libido": "Moderate",
        "modifiedAt": 1686561121534,
        "pain": "ModeratePain",
        "rest": "Moderate"
      },
      {
        "appetite": "Appropriate",
        "completed": true,
        "createdAt": 1684660321000,
        "energy": "Moderate",
        "focus": "Satisfactory",
        "id": 384,
        "libido": "Moderate",
        "modifiedAt": 1686561121549,
        "pain": "ModeratePain",
        "rest": "Satisfactory"
      },
      {
        "appetite": "ExcessivelyHigh",
        "completed": true,
        "createdAt": 1684573921000,
        "energy": "Moderate",
        "focus": "Moderate",
        "id": 385,
        "libido": "Moderate",
        "modifiedAt": 1686561121568,
        "pain": "NoPain",
        "rest": "Moderate"
      },
      {
        "appetite": "ExcessivelyHigh",
        "completed": true,
        "createdAt": 1684487521000,
        "energy": "Moderate",
        "focus": "Satisfactory",
        "id": 386,
        "libido": "Satisfactory",
        "modifiedAt": 1686561121598,
        "pain": "NoPain",
        "rest": "Moderate"
      },
      {
        "appetite": "ExcessivelyHigh",
        "completed": true,
        "createdAt": 1684401121000,
        "energy": "High",
        "focus": "Satisfactory",
        "id": 387,
        "libido": "Moderate",
        "modifiedAt": 1686561121620,
        "pain": "NoPain",
        "rest": "Moderate"
      },
      {
        "appetite": "ExcessivelyHigh",
        "completed": true,
        "createdAt": 1684314721000,
        "energy": "Moderate",
        "focus": "Moderate",
        "id": 388,
        "libido": "Moderate",
        "modifiedAt": 1686561121639,
        "pain": "ModeratePain",
        "rest": "Satisfactory"
      },
      {
        "appetite": "Appropriate",
        "completed": true,
        "createdAt": 1684228321000,
        "energy": "High",
        "focus": "Satisfactory",
        "id": 389,
        "libido": "Moderate",
        "modifiedAt": 1686561121667,
        "pain": "ModeratePain",
        "rest": "Moderate"
      },
      {
        "appetite": "Appropriate",
        "completed": true,
        "createdAt": 1684141921000,
        "energy": "High",
        "focus": "Satisfactory",
        "id": 390,
        "libido": "Satisfactory",
        "modifiedAt": 1686561121687,
        "pain": "NoPain",
        "rest": "Moderate"
      },
      {
        "appetite": "Appropriate",
        "completed": true,
        "createdAt": 1684055521000,
        "energy": "Moderate",
        "focus": "Moderate",
        "id": 391,
        "libido": "Moderate",
        "modifiedAt": 1686561121713,
        "pain": "ModeratePain",
        "rest": "Moderate"
      }
    ]
  },
  "userId": "d3cda405fce54a4fd7ed104a3a675d157e0237fab18527d9089746da2f139836e16c85d68164ff0c684f8508782ca26ec650a8f7027ad31d3dab70300543a220"
}